neuralinit/__init__.py
neuralinit/builder.py
neuralinit-0.1.0.dist-info/LICENSE
neuralinit-0.1.0.dist-info/METADATA
neuralinit-0.1.0.dist-info/WHEEL
neuralinit-0.1.0.dist-info/entry_points.txt
neuralinit-0.1.0.dist-info/top_level.txt
neuralinit-0.1.0.dist-info/RECORD
